tf_fastmri_data/__init__.py
tf_fastmri_data/config.py
tf_fastmri_data/dataset_builder.py
tf_fastmri_data/h5.py
tf_fastmri_data/test_utils.py
tf_fastmri_data/datasets/__init__.py
tf_fastmri_data/datasets/cartesian.py
tf_fastmri_data/datasets/noisy.py
tf_fastmri_data/datasets/non_cartesian.py
tf_fastmri_data/preprocessing_utils/__init__.py
tf_fastmri_data/preprocessing_utils/crop.py
tf_fastmri_data/preprocessing_utils/extract_smaps.py
tf_fastmri_data/preprocessing_utils/masking.py
tf_fastmri_data/preprocessing_utils/non_cartesian_trajectories.py
tf_fastmri_data/preprocessing_utils/scaling.py
tf_fastmri_data/preprocessing_utils/size_adjustment.py
tf_fastmri_data/preprocessing_utils/fourier/__init__.py
tf_fastmri_data/preprocessing_utils/fourier/cartesian.py
tf_fastmri_data/preprocessing_utils/fourier/non_cartesian.py
tf_fastmri_data-0.0.6.dist-info/LICENSE
tf_fastmri_data-0.0.6.dist-info/METADATA
tf_fastmri_data-0.0.6.dist-info/WHEEL
tf_fastmri_data-0.0.6.dist-info/top_level.txt
tf_fastmri_data-0.0.6.dist-info/RECORD
