Metadata-Version: 2.1
Name: tf-fastmri-data
Version: 0.0.6
Summary: Data pipelines for the fastMRI dataset in TensorFlow.
Home-page: https://github.com/zaccharieramzi/tf-fastmri-data
Author: Zaccharie Ramzi
Author-email: zaccharie.ramzi@gmail.com
License: MIT
Platform: UNKNOWN
Classifier: Programming Language :: Python :: 3
Classifier: License :: OSI Approved :: MIT License
Classifier: Operating System :: OS Independent
Requires-Python: >=3.6
License-File: LICENSE
Requires-Dist: h5py
Requires-Dist: ismrmrd
Requires-Dist: numpy
Requires-Dist: tensorflow (>=2.2)
Requires-Dist: tensorflow-io (>=0.15.0)
Requires-Dist: tfkbnufft
